nvidia/__init__.py
nvidia/cuda_nvcc/__init__.py
nvidia/cuda_nvcc/bin/__init__.py
nvidia/cuda_nvcc/bin/ptxas.exe
nvidia/cuda_nvcc/include/__init__.py
nvidia/cuda_nvcc/include/fatbinary_section.h
nvidia/cuda_nvcc/include/nvPTXCompiler.h
nvidia/cuda_nvcc/include/crt/common_functions.h
nvidia/cuda_nvcc/include/crt/cudacc_ext.h
nvidia/cuda_nvcc/include/crt/device_double_functions.h
nvidia/cuda_nvcc/include/crt/device_double_functions.hpp
nvidia/cuda_nvcc/include/crt/device_fp128_functions.h
nvidia/cuda_nvcc/include/crt/device_functions.h
nvidia/cuda_nvcc/include/crt/device_functions.hpp
nvidia/cuda_nvcc/include/crt/func_macro.h
nvidia/cuda_nvcc/include/crt/host_config.h
nvidia/cuda_nvcc/include/crt/host_defines.h
nvidia/cuda_nvcc/include/crt/host_runtime.h
nvidia/cuda_nvcc/include/crt/math_functions.h
nvidia/cuda_nvcc/include/crt/math_functions.hpp
nvidia/cuda_nvcc/include/crt/mma.h
nvidia/cuda_nvcc/include/crt/mma.hpp
nvidia/cuda_nvcc/include/crt/sm_100_rt.h
nvidia/cuda_nvcc/include/crt/sm_100_rt.hpp
nvidia/cuda_nvcc/include/crt/sm_70_rt.h
nvidia/cuda_nvcc/include/crt/sm_70_rt.hpp
nvidia/cuda_nvcc/include/crt/sm_80_rt.h
nvidia/cuda_nvcc/include/crt/sm_80_rt.hpp
nvidia/cuda_nvcc/include/crt/sm_90_rt.h
nvidia/cuda_nvcc/include/crt/sm_90_rt.hpp
nvidia/cuda_nvcc/include/crt/storage_class.h
nvidia/cuda_nvcc/nvvm/bin/nvvm64_40_0.dll
nvidia/cuda_nvcc/nvvm/include/nvvm.h
nvidia/cuda_nvcc/nvvm/libdevice/libdevice.10.bc
nvidia_cuda_nvcc_cu12-12.8.93.dist-info/License.txt
nvidia_cuda_nvcc_cu12-12.8.93.dist-info/METADATA
nvidia_cuda_nvcc_cu12-12.8.93.dist-info/WHEEL
nvidia_cuda_nvcc_cu12-12.8.93.dist-info/top_level.txt
nvidia_cuda_nvcc_cu12-12.8.93.dist-info/RECORD
